itkConfig.py
itk/concrt140.dll
itk/itkAffineTransformPython.py
itk/itkAnnulusOperatorPython.py
itk/itkArray2DPython.py
itk/itkArrayPython.py
itk/itkAzimuthElevationToCartesianTransformPython.py
itk/itkBackwardDifferenceOperatorPython.py
itk/itkBinaryGeneratorImageFilterPython.py
itk/itkBinaryMask3DMeshSourcePython.py
itk/itkBinShrinkImageFilterPython.py
itk/itkBMPImageIOPython.py
itk/itkBoundingBoxPython.py
itk/itkBoxImageFilterPython.py
itk/ITKBridgeNumPyPython.py
itk/itkBSplineBaseTransformPython.py
itk/itkBSplineDecompositionImageFilterPython.py
itk/itkBSplineDownsampleImageFilterPython.py
itk/itkBSplineInterpolateImageFunctionPython.py
itk/itkBSplineInterpolationWeightFunctionPython.py
itk/itkBSplineResampleImageFunctionPython.py
itk/itkBSplineTransformInitializerPython.py
itk/itkBSplineTransformPython.py
itk/itkBSplineUpsampleImageFilterPython.py
itk/itkBYUMeshIOPython.py
itk/itkCastImageFilterPython.py
itk/itkCenteredAffineTransformPython.py
itk/itkCenteredEuler3DTransformPython.py
itk/itkCenteredRigid2DTransformPython.py
itk/itkCenteredSimilarity2DTransformPython.py
itk/itkChangeInformationImageFilterPython.py
itk/ITKCommonBasePython.py
itk/ITKCommonPython.py
itk/itkComparisonImageFilterPython.py
itk/itkComplexToComplex1DFFTImageFilterPython.py
itk/itkComplexToComplexFFTImageFilterPython.py
itk/itkComposeScaleSkewVersor3DTransformPython.py
itk/itkCompositeTransformPython.py
itk/itkConnectedRegionsMeshFilterPython.py
itk/itkConstantPadImageFilterPython.py
itk/itkContinuousIndexPython.py
itk/itkCovariantVectorPython.py
itk/itkCropImageFilterPython.py
itk/itkCyclicShiftImageFilterPython.py
itk/itkDefaultDynamicMeshTraitsPython.py
itk/itkDefaultStaticMeshTraitsPython.py
itk/itkDenseFiniteDifferenceImageFilterPython.py
itk/itkDerivativeOperatorPython.py
itk/itkDiffusionTensor3DPython.py
itk/itkDistanceMetricPython.py
itk/itkElasticBodyReciprocalSplineKernelTransformPython.py
itk/itkElasticBodySplineKernelTransformPython.py
itk/itkEuclideanDistanceMetricPython.py
itk_core-5.4.4.post1.dist-info/DELVEWHEEL
itk_core-5.4.4.post1.dist-info/METADATA
itk_core-5.4.4.post1.dist-info/RECORD
itk_core-5.4.4.post1.dist-info/WHEEL
itk_core-5.4.4.post1.dist-info/licenses/LICENSE
itk_core-5.4.4.post1.dist-info/licenses/ITK-source/ITK/LICENSE
itk_core-5.4.4.post1.dist-info/licenses/ITK-source/ITK/NOTICE
